[
  {
    "info": "25-09-2020_17_06_29"
  },
  {
    "requirements": {
      "TR1": "79,82",
      "TR2": "82,83",
      "TR3": "83,84",
      "TR4": "84,85",
      "TR5": "85,86",
      "TR6": "86,87",
      "TR7": "96,97",
      "TR8": "104,105",
      "TR9": "105,107",
      "TR10": "107,108",
      "TR11": "108,109",
      "TR12": "109,113",
      "TR13": "109,110",
      "TR14": "110,109",
      "TR15": "122,123",
      "TR16": "133,134",
      "TR17": "134,135",
      "TR18": "135,136",
      "TR19": "146,147",
      "TR20": "147,148",
      "TR21": "148,149",
      "TR22": "159,160",
      "TR23": "160,161",
      "TR24": "160,163",
      "TR25": "161,163",
      "TR26": "163,164",
      "TR27": "164,165",
      "TR28": "182,184",
      "TR29": "184,186",
      "TR30": "186,187",
      "TR31": "187,188",
      "TR32": "188,192",
      "TR33": "188,189",
      "TR34": "189,188",
      "TR35": "199,200",
      "TR36": "200,202",
      "TR37": "202,203",
      "TR38": "203,207",
      "TR39": "203,204",
      "TR40": "204,203",
      "TR41": "207,208",
      "TR42": "208,215",
      "TR43": "208,209",
      "TR44": "209,212",
      "TR45": "209,210",
      "TR46": "210,209",
      "TR47": "212,208",
      "TR48": "233,235",
      "TR49": "235,236",
      "TR50": "236,237",
      "TR51": "237,238",
      "TR52": "237,240",
      "TR53": "240,241"
    }
  },
  {
    "testCoverage": {
      "testDerivative": [
        "TR2",
        "TR3",
        "TR4",
        "TR5",
        "TR6",
        "TR49",
        "TR50",
        "TR52",
        "TR8",
        "TR9",
        "TR10",
        "TR11",
        "TR13",
        "TR14",
        "TR12"
      ],
      "testLinearFunction": [
        "TR2",
        "TR3",
        "TR4",
        "TR5",
        "TR6",
        "TR49",
        "TR50",
        "TR52",
        "TR7",
        "TR29",
        "TR30",
        "TR31",
        "TR33",
        "TR34",
        "TR32",
        "TR15",
        "TR22",
        "TR23",
        "TR25",
        "TR26",
        "TR27",
        "TR35",
        "TR36",
        "TR37",
        "TR39",
        "TR40",
        "TR38",
        "TR41",
        "TR43",
        "TR45",
        "TR46",
        "TR44",
        "TR47",
        "TR42"
      ],
      "testParameters": [
        "TR49",
        "TR50",
        "TR52",
        "TR53"
      ],
      "testQuadraticFunction": [
        "TR2",
        "TR3",
        "TR4",
        "TR5",
        "TR6",
        "TR49",
        "TR50",
        "TR52",
        "TR7",
        "TR29",
        "TR30",
        "TR31",
        "TR33",
        "TR34",
        "TR32",
        "TR15",
        "TR22",
        "TR23",
        "TR25",
        "TR26",
        "TR27",
        "TR35",
        "TR36",
        "TR37",
        "TR39",
        "TR40",
        "TR38",
        "TR41",
        "TR43",
        "TR45",
        "TR46",
        "TR44",
        "TR47",
        "TR42"
      ],
      "testQuinticFunction": [
        "TR2",
        "TR3",
        "TR4",
        "TR5",
        "TR6",
        "TR49",
        "TR50",
        "TR52",
        "TR7",
        "TR29",
        "TR30",
        "TR31",
        "TR33",
        "TR34",
        "TR32",
        "TR15",
        "TR22",
        "TR23",
        "TR25",
        "TR26",
        "TR27",
        "TR35",
        "TR36",
        "TR37",
        "TR39",
        "TR40",
        "TR38",
        "TR41",
        "TR43",
        "TR45",
        "TR46",
        "TR44",
        "TR47",
        "TR42"
      ]
    }
  }
]