{
  "sourceCodeStatus": {
    "line": [
      0,
      "227",
      "224",
      "188",
      "195",
      "219",
      "198",
      "207",
      "205",
      "204",
      "228",
      "197",
      "190",
      "214",
      "210",
      "216",
      "193",
      "212",
      "200"
    ],
    "sourceClass": "DefaultParser"
  },
  "testCodeStatus": {
    "affectedReq": [
      "TR24"
    ],
    "deletedRequirementYesTest": [
      "TR27",
      "TR39",
      "TR46",
      "TR25",
      "TR32",
      "TR42",
      "TR41",
      "TR44",
      "TR29",
      "TR31",
      "TR47",
      "TR48",
      "TR34",
      "TR33",
      "TR38",
      "TR26",
      "TR40",
      "TR36",
      "TR28",
      "TR35",
      "TR43",
      "TR45",
      "TR30",
      "TR37"
    ],
    "affectedTest": [
      "testPropertyOptionFlags",
      "testPropertyOptionGroup",
      "testPropertyOptionRequired",
      "testPropertyOptionMultipleValues",
      "testPropertyOptionSingularValue",
      "testPropertyOptionUnexpected",
      "testAmbiguousLongWithoutEqualSingleDash",
      "testArgumentStartingWithHyphen",
      "testBursting",
      "testDoubleDash1",
      "testLongWithEqualDoubleDash",
      "testLongWithEqualSingleDash",
      "testLongWithoutEqualDoubleDash",
      "testLongWithoutEqualSingleDash",
      "testMissingRequiredGroup",
      "testMissingRequiredOption",
      "testMissingRequiredOptions",
      "testMultiple",
      "testMultipleWithLong",
      "testNegativeArgument",
      "testNegativeOption",
      "testOptionAndRequiredOption",
      "testOptionGroup",
      "testOptionGroupLong",
      "testPartialLongOptionSingleDash",
      "testPropertiesOption1",
      "testPropertiesOption2",
      "testReuseOptionsTwice",
      "testShortWithEqual",
      "testShortWithoutEqual",
      "testSimpleLong",
      "testSimpleShort",
      "testSingleDash",
      "testStopAtExpectedArg",
      "testStopAtNonOptionLong",
      "testStopAtNonOptionShort",
      "testStopAtUnexpectedArg",
      "testStopBursting",
      "testStopBursting2",
      "testUnambiguousPartialLongOption1",
      "testUnambiguousPartialLongOption2",
      "testUnambiguousPartialLongOption3",
      "testUnambiguousPartialLongOption4",
      "testUnlimitedArgs",
      "testWithRequiredOption"
    ],
    "testReran": [
      "testNegativeArgument",
      "testPropertyOptionFlags",
      "testStopBursting",
      "testStopAtNonOptionShort",
      "testSimpleLong",
      "testMissingRequiredGroup",
      "testWithRequiredOption",
      "testMultiple",
      "testShortWithEqual",
      "testShortWithoutEqual",
      "testPropertyOptionGroup",
      "testPropertyOptionUnexpected",
      "testUnambiguousPartialLongOption1",
      "testPropertyOptionSingularValue",
      "testNegativeOption",
      "testSingleDash",
      "testPropertyOptionRequired",
      "testSimpleShort",
      "testUnambiguousPartialLongOption4",
      "testAmbiguousLongWithoutEqualSingleDash",
      "testLongWithoutEqualDoubleDash",
      "testMissingRequiredOption",
      "testOptionGroupLong",
      "testArgumentStartingWithHyphen",
      "testOptionAndRequiredOption",
      "testUnlimitedArgs",
      "testLongWithoutEqualSingleDash",
      "testMissingRequiredOptions",
      "testStopAtNonOptionLong",
      "testLongWithEqualDoubleDash",
      "testPropertyOptionMultipleValues",
      "testDoubleDash1",
      "testPartialLongOptionSingleDash",
      "testPropertiesOption1",
      "testReuseOptionsTwice",
      "testMultipleWithLong",
      "testUnambiguousPartialLongOption2",
      "testLongWithEqualSingleDash",
      "testUnambiguousPartialLongOption3",
      "testStopAtExpectedArg",
      "testOptionGroup",
      "testPropertiesOption2",
      "testStopAtUnexpectedArg",
      "testStopBursting2",
      "testBursting"
    ],
    "unsatisfiedRequirement": [
      "TR24",
      "TR27",
      "TR46",
      "TR44",
      "TR29",
      "TR48",
      "TR37"
    ],
    "newTestRequirement": [
      "TR40",
      "TR28",
      "TR25",
      "TR32",
      "TR46",
      "TR48"
    ]
  }
}