{
  "sourceCodeStatus": {
    "line": [
      "56"
    ],
    "sourceClass": "GnuParser"
  },
  "testCodeStatus": {
    "affectedReq": [
      "TR36",
      "TR7",
      "TR6",
      "TR5",
      "TR3",
      "TR4",
      "TR34"
    ],
    "affectedTest": [
      "testArgumentStartingWithHyphen",
      "testDoubleDash1",
      "testLongWithEqualDoubleDash",
      "testLongWithEqualSingleDash",
      "testLongWithoutEqualDoubleDash",
      "testMissingArg",
      "testMissingRequiredGroup",
      "testMissingRequiredOption",
      "testMissingRequiredOptions",
      "testMultiple",
      "testMultipleWithLong",
      "testNegativeArgument",
      "testOptionAndRequiredOption",
      "testOptionGroup",
      "testOptionGroupLong",
      "testPropertiesOption1",
      "testPropertiesOption2",
      "testPropertyOptionFlags",
      "testPropertyOptionGroup",
      "testPropertyOptionMultipleValues",
      "testPropertyOptionRequired",
      "testPropertyOptionSingularValue",
      "testPropertyOptionUnexpected",
      "testReuseOptionsTwice",
      "testShortWithEqual",
      "testShortWithoutEqual",
      "testSimpleLong",
      "testSimpleShort",
      "testSingleDash",
      "testStopAtExpectedArg",
      "testStopAtNonOptionLong",
      "testStopAtNonOptionShort",
      "testStopAtUnexpectedArg",
      "testUnlimitedArgs",
      "testUnrecognizedOption",
      "testWithRequiredOption"
    ],
    "testReran": [
      "testMissingRequiredOption",
      "testPropertyOptionRequired",
      "testShortWithEqual",
      "testReuseOptionsTwice",
      "testSimpleLong",
      "testSimpleShort",
      "testStopAtExpectedArg",
      "testUnrecognizedOption",
      "testStopAtNonOptionLong",
      "testPropertyOptionUnexpected",
      "testPropertyOptionMultipleValues",
      "testPropertiesOption2",
      "testPropertiesOption1",
      "testNegativeArgument",
      "testLongWithEqualSingleDash",
      "testStopAtNonOptionShort",
      "testPropertyOptionGroup",
      "testMultiple",
      "testArgumentStartingWithHyphen",
      "testUnlimitedArgs",
      "testLongWithEqualDoubleDash",
      "testOptionGroupLong",
      "testSingleDash",
      "testMissingArg",
      "testOptionGroup",
      "testMissingRequiredOptions",
      "testMissingRequiredGroup",
      "testOptionAndRequiredOption",
      "testStopAtUnexpectedArg",
      "testDoubleDash1",
      "testLongWithoutEqualDoubleDash",
      "testPropertyOptionFlags",
      "testPropertyOptionSingularValue",
      "testShortWithoutEqual",
      "testMultipleWithLong",
      "testWithRequiredOption"
    ],
    "unsatisfiedRequirement": [
      "TR7",
      "TR4"
    ]
  }
}